[
  {
    "id": "1",
    "title": "Animateur saisonnier en Camping",
    "company": "Marmotel Saint Geniez d'Olt",
    "description": "J'ai animé un camping de 550 vacanciers pendant plus de 2 mois",
    "timePeriod": "Juillet & Août 2021",
    "img": "images/camping.webp"
  },
  {
    "id": "2",
    "title": "Champion de France de tennis de table",
    "company": "Nantes",
    "description": "A 15 ans, je remporte les championnats de France par classement dans ma catégorie",
    "timePeriod": "Juin 2015",
    "img": "images/ping.webp"
  }
  
]